gierto.py
gitopen.py
gierto-0.0.1.dist-info/DESCRIPTION.rst
gierto-0.0.1.dist-info/METADATA
gierto-0.0.1.dist-info/RECORD
gierto-0.0.1.dist-info/WHEEL
gierto-0.0.1.dist-info/entry_points.txt
gierto-0.0.1.dist-info/metadata.json
gierto-0.0.1.dist-info/top_level.txt
