Metadata-Version: 2.0
Name: gierto
Version: 0.0.1
Summary: A command line tool for opening Git repository page in your browser
Home-page: https://github.com/suzaku/gierto
Author: satoru
Author-email: satorulogic@gmail.com
License: MIT
Platform: UNKNOWN
Classifier: Development Status :: 3 - Alpha
Classifier: Intended Audience :: Developers
Classifier: License :: OSI Approved :: MIT License
Classifier: Programming Language :: Python :: 2
Classifier: Programming Language :: Python :: 2.7
